roboglia/__init__.py
roboglia/_version.py
roboglia/base/__init__.py
roboglia/base/bus.py
roboglia/base/device.py
roboglia/base/joint.py
roboglia/base/register.py
roboglia/base/robot.py
roboglia/base/sensor.py
roboglia/base/sync.py
roboglia/base/thread.py
roboglia/base/devices/DUMMY.yml
roboglia/dynamixel/__init__.py
roboglia/dynamixel/bus.py
roboglia/dynamixel/device.py
roboglia/dynamixel/sync.py
roboglia/dynamixel/devices/2XC430-W250.yml
roboglia/dynamixel/devices/2XL430.yml
roboglia/dynamixel/devices/AX-12A.yml
roboglia/dynamixel/devices/AX-18A.yml
roboglia/dynamixel/devices/MX-106.yml
roboglia/dynamixel/devices/MX-106v2.yml
roboglia/dynamixel/devices/MX-28.yml
roboglia/dynamixel/devices/MX-28v2.yml
roboglia/dynamixel/devices/MX-64.yml
roboglia/dynamixel/devices/MX-64v2.yml
roboglia/dynamixel/devices/XC430-W150.yml
roboglia/dynamixel/devices/XC430-W240.yml
roboglia/dynamixel/devices/XL-320.yml
roboglia/dynamixel/devices/XL430.yml
roboglia/i2c/__init__.py
roboglia/i2c/bus.py
roboglia/i2c/device.py
roboglia/i2c/sync.py
roboglia/i2c/devices/DUMMY.yml
roboglia/i2c/devices/LSM330G.yml
roboglia/i2c/devices/LSM6DS3.yml
roboglia/i2c/devices/TCA9538.yml
roboglia/i2c/devices/TLA202x.yml
roboglia/move/__init__.py
roboglia/move/moves.py
roboglia/move/thread.py
roboglia/utils/__init__.py
roboglia/utils/checks.py
roboglia/utils/factory.py
roboglia-0.1.0.dist-info/LICENCE.txt
roboglia-0.1.0.dist-info/METADATA
roboglia-0.1.0.dist-info/WHEEL
roboglia-0.1.0.dist-info/top_level.txt
roboglia-0.1.0.dist-info/RECORD
