Metadata-Version: 2.1
Name: roboglia
Version: 0.1.0
Summary: Robotics Framework using Dynamixel SDK, I2C, SPI
Home-page: https://github.com/sonelu/roboglia
Author: Alex Sonea
Author-email: alex.sonea@gmail.com
License: GNU GENERAL PUBLIC LICENSE Version 3
Project-URL: Documentation, https://roboglia.readthedocs.io/en/latest/
Project-URL: Bug tracker, https://github.com/sonelu/roboglia/issues
Project-URL: Installation, https://roboglia.readthedocs.io/en/latest/install.html
Platform: UNKNOWN
Classifier: Programming Language :: Python :: 3
Classifier: Topic :: Scientific/Engineering
Requires-Dist: pyyaml
Provides-Extra: all
Requires-Dist: spidev ; extra == 'all'
Requires-Dist: smbus2 ; extra == 'all'
Requires-Dist: dynamixel-sdk ; extra == 'all'
Provides-Extra: dynamixel
Requires-Dist: dynamixel-sdk ; extra == 'dynamixel'
Provides-Extra: i2c
Requires-Dist: smbus2 ; extra == 'i2c'
Provides-Extra: spi
Requires-Dist: spidev ; extra == 'spi'
